django_aws_ses/__init__.py
django_aws_ses/admin.py
django_aws_ses/apps.py
django_aws_ses/backends.py
django_aws_ses/models.py
django_aws_ses/settings.py
django_aws_ses/signals.py
django_aws_ses/tests.py
django_aws_ses/urls.py
django_aws_ses/utils.py
django_aws_ses/views.py
django_aws_ses/migrations/0001_initial.py
django_aws_ses/migrations/0002_remove_awssessettings.py
django_aws_ses/migrations/__init__.py
django_aws_ses/static/django_aws_ses/favicon.ico
django_aws_ses/static/django_aws_ses/css/base.css
django_aws_ses/static/django_aws_ses/css/send_stats.css
django_aws_ses/static/django_aws_ses/css/unsubscribe.css
django_aws_ses/static/django_aws_ses/js/chart.min.js
django_aws_ses/templates/django_aws_ses/base.html
django_aws_ses/templates/django_aws_ses/send_stats.html
django_aws_ses/templates/django_aws_ses/unsubscribe.html
django_aws_ses-0.1.5.dist-info/licenses/LICENSE
django_aws_ses-0.1.5.dist-info/METADATA
django_aws_ses-0.1.5.dist-info/WHEEL
django_aws_ses-0.1.5.dist-info/top_level.txt
django_aws_ses-0.1.5.dist-info/RECORD
