Metadata-Version: 2.4
Name: django_aws_ses
Version: 0.1.5
Summary: A Django email backend for Amazon SES with bounce and complaint handling
Home-page: https://github.com/zeeksgeeks/django_aws_ses
Author: ZeeksGeeks
Author-email: contact@zeeksgeeks.com
Classifier: Programming Language :: Python :: 3
Classifier: License :: OSI Approved :: MIT License
Classifier: Operating System :: OS Independent
Classifier: Framework :: Django
Requires-Python: >=3.6
License-File: LICENSE
Requires-Dist: django>=3.2
Requires-Dist: boto3>=1.18.0
Requires-Dist: requests>=2.26.0
Requires-Dist: cryptography>=3.4.7
Requires-Dist: dnspython>=2.1.0
Provides-Extra: dev
Requires-Dist: pytest>=7.0.0; extra == "dev"
Requires-Dist: pytest-django>=4.5.0; extra == "dev"
Requires-Dist: mock>=4.0.3; extra == "dev"
Provides-Extra: dkim
Requires-Dist: dkimpy>=1.0.0; extra == "dkim"
Dynamic: author
Dynamic: author-email
Dynamic: classifier
Dynamic: description
Dynamic: description-content-type
Dynamic: home-page
Dynamic: license-file
Dynamic: provides-extra
Dynamic: requires-dist
Dynamic: requires-python
Dynamic: summary
